{
    "now": {
        "og": ["「北川ひかる選手」", "「安部裕葵選手」","「藤井海和選手」","「倉持快選手」","「松本大輔選手」"],
        "dt": ["POSITION"],
        "dd": ["DF：ディフェンダー","FW：フォワード","MF：ミッドフィールダー","MF：ミッドフィールダー","DF：ディフェンダー"],
        "point1": ["圧倒的なスピード","チャンスメーク","圧倒的な守備","圧倒的なスピード","優位な高身長"],
        "point2": ["希少な左利き","鋭いドリブル","メンタリティの強さ","抜群の瞬発力","判断能力の高さ"],
        "p": [
            "北川ひかる選手はスピードあり左利きという極めて珍しい特徴持っています。ぜひ彼女のプレイを参考にしてみて下さい！",
            "安部裕葵選手はスピードに乗った鋭いドリブルを武器に味方を生かしてゴールに直結するという特徴を持っています。ぜひ彼のププレイを参考にしてみて下さい！",
            "藤井海和選手は相手のパスコースを的確に切りながらの守備と持前のメンタリティの強さが特徴です。ぜひ彼のププレイを参考にしてみて下さい！",
            "倉持快選手はスピードを生かした突破と抜群の瞬発力を生かしたプレーが特徴です。ぜひ彼のププレイを参考にしてみて下さい！",
            "安部裕葵選手はスピードに乗った鋭いドリブルを武器に味方を生かしてゴールに直結するという特徴を持っています。ぜひ彼のププレイを参考にしてみて下さい！"
        ]
    },
    "seiryo": {
        "og": ["「北川ひかる選手」", "ヒカル"],
        "dt": ["DF・MF", "ヒカル"],
        "dd": ["なでしこジャパン", "ヒカル"],
        "point1": ["圧倒的なスピード"],
        "point2": ["希少な左利き"],
        "img": ["../img/hikaru_img.png", "../img/image01.jpg"],
        "p": [
            "北川ひかる選手はスピードあり左利きという極めて珍しい特徴持っています。彼女のプレイを参考にしてみるといいかも！",
            "ヒカル"
        ]
    },
    "weak": {
        "training": [
            "「フィジカル強化トレーニング」",
            "「テクニック強化トレーニング」",
            "「判断力強化トレーニング」"
        ],
        "point": ["自由にコントロール", "スキルを向上できる", "⾃ら判断する力"],
        "dt": ["SOLTILO"],
        "dd": ["育成メソッド"],
        "p": [
            "⾃分の⾝体を⾃由⾃在にコントロールできるベース作りをSoltiloでは徹底しています。",
            "各年代に必要な判断を伴ったスキルの向上をSoltiloでは徹底しています。",
            "多くの選択肢を持ち、⾃ら判断し選択・決断する力をSoltiloでは徹底しています。"
        ]
    },
    "good": {
        "chiba": {
            "staff": [
                "「橋本 雄二監督」",
                "「林 晋太郎コーチ」",
                "「半澤 祐治コーチ」",
                "「後藤 大輔コーチ」"
            ],
            "point": [
                "技術面をサポート",
                "優秀なGKを育成",
                "フィジカル面の強化",
                "怪我の対策を徹底"
            ],
            "dt": ["SOLTILO STAFF"],
            "dd": [
                "U-18監督",
                "GKコーチ",
                "フィジカルコーチ",
                "アスレチックトレーナー"
            ],
            "p": [
                "U=18の監督をしています。技術だけでなく精神面も徹底的にサポートしていきます。",
                "優秀な選手を輩出するため、ゴールキーパー選手のトレーニング管理・育成をしています。",
                "選手のフィジカル面でのトレーニング管理、育成をしています。",
                "怪我をしている選手のリハビリ、選手の怪我予防のトレーニング管理をしています。"
            ]
        },
        "tokyo": {
            "staff": [
                "「廣瀬 太郎監督」",
                "「井口 勝コーチ」",
                "「三沢 雅人コーチ」"
            ],
            "point": ["技術面をサポート", "怪我の対策を徹底", "優秀なGKを育成"],
            "dt": ["SOLTILO STAFF"],
            "dd": ["代表・監督", "トレーナー", "GKコーチ"],
            "p": [
                "U=18の監督をしています。技術だけでなく精神面も徹底的にサポートしていきます。",
                "怪我をしている選手のリハビリ、選手の怪我予防のトレーニング管理をしています。",
                "優秀な選手を輩出するため、ゴールキーパー選手のトレーニング管理・育成をしています。"
            ]
        },
        "seiryo": {
            "boys": {
                "staff": ["「松原 徹博監督」"],
                "point": ["技術面をサポート"],
                "dt": ["SOLTILO STAFF"],
                "dd": ["U-15監督"],
                "p": [
                    "U=18の監督をしています。技術だけでなく精神面も徹底的にサポートしていきます。"
                ]
            },
            "ladies": {
                "staff": ["「菅原 渉監督」"],
                "point": ["技術面をサポート"],
                "dt": ["SOLTILO STAFF"],
                "dd": ["LADIS監督"],
                "p": [
                    "LADIESの監督をしています。技術だけでなく精神面も徹底的にサポートしていきます。"
                ]
            }
        },
        "oosaka": {
            "staff": ["「田中 章博代表」", "「松田 淳一コーチ」"],
            "point": ["技術面をサポート", "優秀なGKを育成"],
            "dt": ["SOLTILO STAFF"],
            "dd": ["チーム代表", "GKコーチ"],
            "p": [
                "チーム代表をしています。技術だけでなく精神面も徹底的にサポートしていきます。",
                "優秀な選手を輩出するため、ゴールキーパー選手のトレーニング管理・育成をしています。"
            ]
        }
    },
    "slider": {
        "player": [
            "小川颯斗選手",
            "三橋裕斗選手",
            "高山敦広選手",
            "古川憧選手",
            "佐藤弦都選手",
            "丸隼磨選手"
        ],
        "p": [
            "SOLTILOに入って技術だけでなく精神的にも成長することができた。",
            "技術だけでなく精神的にも成長することができた。",
            "SOLTILOに入って技術だけでなく精神的にも成長することができた。",
            "技術だけでなく精神的にも成長することができた。",
            "SOLTILOに入って技術だけでなく精神的にも成長することができた。",
            "技術だけでなく精神的にも成長することができた。"
        ]
    },
    "check": {
        "tracking": {
            "title": "トラッキングシステム",
            "point": "＃技術でサポート",
            "p": "運動中に身につけプレー中のデータを蓄積することによって事実と理論に基づいた的確なパフォーマンス向上の指導・育成を実現しています。"
        },
        "gkcoach": {
            "title": "GKコーチ",
            "point": "＃GK選手をサポート",
            "p": "優秀な選手を輩出するため、ゴールキーパー選手のトレーニング管理・育成をしています。"
        },
        "lawn": {
            "title": "人工芝生",
            "point": "＃環境を整備",
            "p": "SOLTILO CHIBAではすべて人工芝で完備されたZOZOPARK HONDA FOOTBALL AREAを使用しています。最適な環境作りは子供たちの育成・教育に欠かせないと考えています。"
        },
        "dormitory": {
            "title": "選手寮",
            "point": "＃地方の選手を応援",
            "p": "SOLTILO CHIBAではトレーニング場から徒歩10分の程度のところに選手寮を完備しています。選手寮にはスタッフが常駐して、食事の栄養管理も行っております。"
        },
        "expedition": {
            "title": "海外遠征",
            "point": "＃世界に挑戦",
            "p": "世界トップのアスリートや施設を間近で見ることによって学べることは多いと思います。そのため、WAHSではチームが海外遠征を実施できるように努めています。",
            "li1":"２０１８年　ミラノ遠征",
            "li2":"２０１９年　バルセロナ遠征",
            "li3":"２０１９年　上海遠征"
        },
        "trainer": {
            "title": "リハビリトレーナー",
            "point": "＃怪我の対策を徹底",
            "p": "怪我をしている選手のリハビリ、選手の怪我予防のトレーニング管理をしています。"
        },
        "knows": {
            "title": "knows",
            "point": "＃技術でサポート",
            "p": "運動中に身につけプレー中のデータを蓄積することによって事実と理論に基づいた的確なパフォーマンス向上の指導・育成を実現しています。"
        },
        "institution": {
            "title": "広い施設",
            "point": "＃環境を整備",
            "p": "最適な環境作りは子供たちの育成・教育に欠かせないと考えています。",
            "li1":"ZOZOPARK HONDA FOOTBALL AREA",
            "li2":"SOLTILO金沢大 FIELD (石川金沢/フルコート２面）",
            "li3":"清瀬内山公園運動公園（東京清瀬市/指定管理施設）"

        },
        "physicalcoach": {
            "title": "フィジカルコーチ",
            "point": "＃怪我の対策を徹底",
            "p": "怪我をしている選手のリハビリ、選手の怪我予防のトレーニング管理をしています。"
        },
        "foreigner": {
            "title": "外国人選手",
            "point": "＃コミュニケーション",
            "p": "言葉の通じないチームメイトと時間を共にすることで各選手のコミュニケーション能力の向上、そしてグループ価値の向上も期待できます。",
            "li1":"韓国・中国・カンボジア",
            "li2":"メキシコ・パラグアイ",
            "li3":"ケニア"
        },
        "sponser": {
            "title": "スポンサー",
            "point": "＃選手をサポート",
            "p": "いつもご協賛いただき、ありがとうございます。"
        },
        "personalgym": {
            "title": "パーソナルジム",
            "point": "＃技術をサポート",
            "p": "パーソナルジムと連携させて選手の技術を促進させています。"
        }
    }
}
